odoo/addons/web_send_message_popup/README.rst
odoo/addons/web_send_message_popup/__init__.py
odoo/addons/web_send_message_popup/__manifest__.py
odoo/addons/web_send_message_popup/i18n/ca.po
odoo/addons/web_send_message_popup/i18n/es.po
odoo/addons/web_send_message_popup/i18n/pt_BR.po
odoo/addons/web_send_message_popup/i18n/web_send_message_popup.pot
odoo/addons/web_send_message_popup/i18n/zh_CN.po
odoo/addons/web_send_message_popup/readme/CONTRIBUTORS.rst
odoo/addons/web_send_message_popup/readme/DESCRIPTION.rst
odoo/addons/web_send_message_popup/static/description/icon.png
odoo/addons/web_send_message_popup/static/description/index.html
odoo/addons/web_send_message_popup/static/src/js/chatter.js
odoo/addons/web_send_message_popup/templates/assets.xml
odoo12_addon_web_send_message_popup-12.0.1.0.0.99.dev10.dist-info/METADATA
odoo12_addon_web_send_message_popup-12.0.1.0.0.99.dev10.dist-info/WHEEL
odoo12_addon_web_send_message_popup-12.0.1.0.0.99.dev10.dist-info/top_level.txt
odoo12_addon_web_send_message_popup-12.0.1.0.0.99.dev10.dist-info/RECORD
